{
    "inJsonObj": {
        "welcomePage": {
            "welcomeIntro": "歡迎使用此小幫手，此小幫手可以幫你將你的學生的成績{0}依照個別的學生{1}輸出其表格，也可以看到所有學生{2}長期的學習趨勢。使用法很簡單，目前只有<b>設定</b>與<b>產生</b>這兩個功能。原始碼在{3}裡",
            "setup": "設定"
        },
        "TestPage": {
            "test": "測試"
        }
    },
    "defaultLang": "zh-tw",
    "ignoreProperties": [
        "address"
    ],
    "outI18nDir": "src/assets/i18n",
    "outDefaultFile": "src/defaultPTS.ts",
    "outInterfaceFile": "src/IPageTexts.ts",
    "interfaceName": "PageTexts",
    "eachJsonFileName": "pageTexts.json"
}